fastmark/baselines.py
fastmark/benchmark_commits.py
fastmark/fastmark.py
fastmark/regexes.py
fastmark/pyperformance/__init__.py
fastmark/pyperformance/__main__.py
fastmark/pyperformance/_benchmark.py
fastmark/pyperformance/_benchmark_metadata.py
fastmark/pyperformance/_benchmark_selections.py
fastmark/pyperformance/_manifest.py
fastmark/pyperformance/_pip.py
fastmark/pyperformance/_pyproject_toml.py
fastmark/pyperformance/_python.py
fastmark/pyperformance/_pythoninfo.py
fastmark/pyperformance/_utils.py
fastmark/pyperformance/_venv.py
fastmark/pyperformance/cli.py
fastmark/pyperformance/commands.py
fastmark/pyperformance/compare.py
fastmark/pyperformance/compile.py
fastmark/pyperformance/run.py
fastmark/pyperformance/venv.py
fastmark/pyperformance/data-files/benchmarks/MANIFEST
fastmark/pyperformance/data-files/benchmarks/bm_2to3/pyproject.toml
fastmark/pyperformance/data-files/benchmarks/bm_2to3/run_benchmark.py
fastmark/pyperformance/data-files/benchmarks/bm_2to3/data/2to3/README.txt
fastmark/pyperformance/data-files/benchmarks/bm_2to3/data/2to3/__init__.py.txt
fastmark/pyperformance/data-files/benchmarks/bm_2to3/data/2to3/context_processors.py.txt
fastmark/pyperformance/data-files/benchmarks/bm_2to3/data/2to3/exceptions.py.txt
fastmark/pyperformance/data-files/benchmarks/bm_2to3/data/2to3/mail.py.txt
fastmark/pyperformance/data-files/benchmarks/bm_2to3/data/2to3/paginator.py.txt
fastmark/pyperformance/data-files/benchmarks/bm_2to3/data/2to3/signals.py.txt
fastmark/pyperformance/data-files/benchmarks/bm_2to3/data/2to3/template_loader.py.txt
fastmark/pyperformance/data-files/benchmarks/bm_2to3/data/2to3/urlresolvers.py.txt
fastmark/pyperformance/data-files/benchmarks/bm_2to3/data/2to3/xheaders.py.txt
fastmark/pyperformance/data-files/benchmarks/bm_2to3/vendor/LICENSE.txt
fastmark/pyperformance/data-files/benchmarks/bm_2to3/vendor/pyproject.toml
fastmark/pyperformance/data-files/benchmarks/bm_2to3/vendor/src/lib2to3/Grammar.txt
fastmark-0.1.4.dist-info/METADATA
fastmark-0.1.4.dist-info/WHEEL
fastmark-0.1.4.dist-info/entry_points.txt
fastmark-0.1.4.dist-info/top_level.txt
fastmark-0.1.4.dist-info/RECORD
